registry.py
py_configs_registry-0.0.2.dist-info/LICENSE
py_configs_registry-0.0.2.dist-info/METADATA
py_configs_registry-0.0.2.dist-info/WHEEL
py_configs_registry-0.0.2.dist-info/top_level.txt
py_configs_registry-0.0.2.dist-info/RECORD
