Metadata-Version: 2.1
Name: py-configs-registry
Version: 0.0.2
Summary: python registry package
Home-page: http://github.com/ztj1993/py_configs_registry
Author: ZhangTianJie
Author-email: ztj1993@gmail.com
License: MIT
Keywords: registry config json yaml
Platform: UNKNOWN
Requires-Dist: mergedict
